target_redshift/__init__.py
target_redshift/db_sync.py
pipelinewise_target_redshift-1.6.0.dist-info/LICENSE
pipelinewise_target_redshift-1.6.0.dist-info/METADATA
pipelinewise_target_redshift-1.6.0.dist-info/WHEEL
pipelinewise_target_redshift-1.6.0.dist-info/entry_points.txt
pipelinewise_target_redshift-1.6.0.dist-info/top_level.txt
pipelinewise_target_redshift-1.6.0.dist-info/RECORD
